{"allDeckData":[{"allPlaySlotData":[{"isEmpty":false,"characterId":7,"lvl":12,"weight":9,"exp":331,"imagePath":"/Canvas/Material/FakeMan"},{"isEmpty":false,"characterId":4,"lvl":1,"weight":2,"exp":13,"imagePath":"/Canvas/Material/FakeMan"},{"isEmpty":false,"characterId":1,"lvl":13,"weight":3,"exp":1103,"imagePath":"/Canvas/Material/NuoNuo_001"},{"isEmpty":false,"characterId":5,"lvl":6,"weight":3,"exp":45,"imagePath":"/Canvas/Material/FakeMan"},{"isEmpty":true,"characterId":-1,"lvl":-1,"weight":-1,"exp":-1,"imagePath":""}],"allRestSlotData":[{"isEmpty":false,"characterId":6,"lvl":7,"weight":6,"exp":26,"imagePath":"/Canvas/Material/FakeMan"},{"isEmpty":false,"characterId":2,"lvl":8,"weight":4,"exp":66,"imagePath":"/Canvas/Material/GuCuBa_001"},{"isEmpty":false,"characterId":3,"lvl":10,"weight":3,"exp":110,"imagePath":"/Canvas/Material/Bruto_001"},{"isEmpty":false,"characterId":0,"lvl":11,"weight":3,"exp":563,"imagePath":"/Canvas/Material/Edward_001"}]},{"allPlaySlotData":[{"isEmpty":false,"characterId":6,"lvl":7,"weight":6,"exp":26,"imagePath":"/Canvas/Material/FakeMan"},{"isEmpty":false,"characterId":2,"lvl":8,"weight":4,"exp":66,"imagePath":"/Canvas/Material/GuCuBa_001"},{"isEmpty":true,"characterId":0,"lvl":0,"weight":0,"exp":0,"imagePath":""},{"isEmpty":true,"characterId":0,"lvl":0,"weight":0,"exp":0,"imagePath":""},{"isEmpty":true,"characterId":0,"lvl":0,"weight":0,"exp":0,"imagePath":""}],"allRestSlotData":[{"isEmpty":false,"characterId":1,"lvl":13,"weight":3,"exp":1103,"imagePath":"/Canvas/Material/NuoNuo_001"},{"isEmpty":false,"characterId":0,"lvl":11,"weight":3,"exp":563,"imagePath":"/Canvas/Material/Edward_001"},{"isEmpty":false,"characterId":3,"lvl":10,"weight":3,"exp":110,"imagePath":"/Canvas/Material/Bruto_001"},{"isEmpty":false,"characterId":5,"lvl":6,"weight":3,"exp":45,"imagePath":"/Canvas/Material/FakeMan"},{"isEmpty":false,"characterId":4,"lvl":1,"weight":2,"exp":13,"imagePath":"/Canvas/Material/FakeMan"},{"isEmpty":false,"characterId":7,"lvl":12,"weight":9,"exp":331,"imagePath":"/Canvas/Material/FakeMan"}]},{"allPlaySlotData":[{"isEmpty":false,"characterId":0,"lvl":11,"weight":3,"exp":563,"imagePath":"/Canvas/Material/Edward_001"},{"isEmpty":false,"characterId":1,"lvl":13,"weight":3,"exp":1103,"imagePath":"/Canvas/Material/NuoNuo_001"},{"isEmpty":false,"characterId":7,"lvl":12,"weight":9,"exp":331,"imagePath":"/Canvas/Material/FakeMan"},{"isEmpty":false,"characterId":5,"lvl":6,"weight":3,"exp":45,"imagePath":"/Canvas/Material/FakeMan"},{"isEmpty":true,"characterId":-1,"lvl":-1,"weight":-1,"exp":-1,"imagePath":""}],"allRestSlotData":[{"isEmpty":false,"characterId":4,"lvl":1,"weight":2,"exp":13,"imagePath":"/Canvas/Material/FakeMan"},{"isEmpty":false,"characterId":6,"lvl":7,"weight":6,"exp":26,"imagePath":"/Canvas/Material/FakeMan"},{"isEmpty":false,"characterId":2,"lvl":8,"weight":4,"exp":66,"imagePath":"/Canvas/Material/GuCuBa_001"},{"isEmpty":false,"characterId":3,"lvl":10,"weight":3,"exp":110,"imagePath":"/Canvas/Material/Bruto_001"}]},{"allPlaySlotData":[{"isEmpty":true,"characterId":0,"lvl":0,"weight":0,"exp":0,"imagePath":""},{"isEmpty":true,"characterId":0,"lvl":0,"weight":0,"exp":0,"imagePath":""},{"isEmpty":true,"characterId":-1,"lvl":-1,"weight":-1,"exp":-1,"imagePath":""},{"isEmpty":true,"characterId":0,"lvl":0,"weight":0,"exp":0,"imagePath":""},{"isEmpty":true,"characterId":0,"lvl":0,"weight":0,"exp":0,"imagePath":""}],"allRestSlotData":[{"isEmpty":false,"characterId":0,"lvl":11,"weight":3,"exp":563,"imagePath":"/Canvas/Material/Edward_001"},{"isEmpty":false,"characterId":1,"lvl":13,"weight":3,"exp":1103,"imagePath":"/Canvas/Material/NuoNuo_001"},{"isEmpty":false,"characterId":2,"lvl":8,"weight":4,"exp":66,"imagePath":"/Canvas/Material/GuCuBa_001"},{"isEmpty":false,"characterId":3,"lvl":10,"weight":3,"exp":110,"imagePath":"/Canvas/Material/Bruto_001"},{"isEmpty":false,"characterId":4,"lvl":1,"weight":2,"exp":13,"imagePath":"/Canvas/Material/FakeMan"},{"isEmpty":false,"characterId":5,"lvl":6,"weight":3,"exp":45,"imagePath":"/Canvas/Material/FakeMan"},{"isEmpty":false,"characterId":6,"lvl":7,"weight":6,"exp":26,"imagePath":"/Canvas/Material/FakeMan"},{"isEmpty":false,"characterId":7,"lvl":12,"weight":9,"exp":331,"imagePath":"/Canvas/Material/FakeMan"}]},{"allPlaySlotData":[{"isEmpty":true,"characterId":0,"lvl":0,"weight":0,"exp":0,"imagePath":""},{"isEmpty":true,"characterId":0,"lvl":0,"weight":0,"exp":0,"imagePath":""},{"isEmpty":true,"characterId":-1,"lvl":-1,"weight":-1,"exp":-1,"imagePath":""},{"isEmpty":true,"characterId":0,"lvl":0,"weight":0,"exp":0,"imagePath":""},{"isEmpty":true,"characterId":-1,"lvl":-1,"weight":-1,"exp":-1,"imagePath":""}],"allRestSlotData":[{"isEmpty":false,"characterId":3,"lvl":10,"weight":3,"exp":110,"imagePath":"/Canvas/Material/Bruto_001"},{"isEmpty":false,"characterId":6,"lvl":7,"weight":6,"exp":26,"imagePath":"/Canvas/Material/FakeMan"},{"isEmpty":false,"characterId":0,"lvl":11,"weight":3,"exp":563,"imagePath":"/Canvas/Material/Edward_001"},{"isEmpty":false,"characterId":1,"lvl":13,"weight":3,"exp":1103,"imagePath":"/Canvas/Material/NuoNuo_001"},{"isEmpty":false,"characterId":2,"lvl":8,"weight":4,"exp":66,"imagePath":"/Canvas/Material/GuCuBa_001"},{"isEmpty":false,"characterId":5,"lvl":6,"weight":3,"exp":45,"imagePath":"/Canvas/Material/FakeMan"},{"isEmpty":false,"characterId":4,"lvl":1,"weight":2,"exp":13,"imagePath":"/Canvas/Material/FakeMan"},{"isEmpty":false,"characterId":7,"lvl":12,"weight":9,"exp":331,"imagePath":"/Canvas/Material/FakeMan"}]}]}